azure_rm_client/README.md
azure_rm_client/client.py
azure_rm_client/cmd.py
azure_rm_client/commands/__init__.py
azure_rm_client/commands/base_command.py
azure_rm_client/commands/fetch_azurermapi_command.py
azure_rm_client/commands/get_all.py
azure_rm_client/commands/list_resources_command.py
azure_rm_client/commands/resource_command.py
azure_rm_client/commands/resource_group_command.py
azure_rm_client/commands/resource_group_commands.py
azure_rm_client/commands/resource_groups_command.py
azure_rm_client/commands/route_tables_command.py
azure_rm_client/commands/subscriptions_command.py
azure_rm_client/commands/virtual_machines_command.py
azure_rm_client/commands/vm_hostnames_command.py
azure_rm_client/commands/vm_reports_command.py
azure_rm_client/commands/vm_shortcuts_command.py
azure_rm_client/core/auth.py
azure_rm_client/create_module_structure.py
azure_rm_client/formatter.py
azure_rm_client/formatters/__init__.py
azure_rm_client/formatters/formatter_interface.py
azure_rm_client/formatters/json_formatter.py
azure_rm_client/formatters/markdown_formatter.py
azure_rm_client/formatters/mediawiki_formatter.py
azure_rm_client/formatters/rich_formatter.py
azure_rm_client/formatters/table_formatter.py
azure_rm_client/formatters/text_formatter.py
azure_rm_client/formatters/yaml_formatter.py
azure_rm_client/requirements.txt
azure_rm_client/tests/test_cmd_subcommands.py
azure_rm_client/tests/test_command_registry.py
azure_rm_client/workers/__init__.py
azure_rm_client/workers/azurerm_api_worker.py
azure_rm_client/workers/resource_groups_worker.py
azure_rm_client/workers/route_tables_worker.py
azure_rm_client/workers/subscriptions_worker.py
azure_rm_client/workers/virtual_machines_worker.py
azure_rm_client/workers/vm_hostnames_worker.py
azure_rm_client/workers/vm_reports_worker.py
azure_rm_client/workers/vm_shortcuts_worker.py
azure_rm_client/workers/worker_base.py
azure_rm_client/workers/worker_factory.py
azure_rm_proxy/api/resource_groups.py
azure_rm_proxy/api/root.py
azure_rm_proxy_server-0.1.20.dist-info/LICENSE
azure_rm_proxy_server-0.1.20.dist-info/METADATA
azure_rm_proxy_server-0.1.20.dist-info/WHEEL
azure_rm_proxy_server-0.1.20.dist-info/entry_points.txt
azure_rm_proxy_server-0.1.20.dist-info/RECORD
