Metadata-Version: 2.3
Name: azure-rm-proxy-server
Version: 0.1.20
Summary: 
Author: Your Name
Author-email: you@example.com
Requires-Python: >=3.10,<4.0
Classifier: Programming Language :: Python :: 3
Classifier: Programming Language :: Python :: 3.10
Classifier: Programming Language :: Python :: 3.11
Classifier: Programming Language :: Python :: 3.12
Classifier: Programming Language :: Python :: 3.13
Requires-Dist: anyio (>=4.9.0,<5.0.0)
Requires-Dist: azure-identity (==1.13.0)
Requires-Dist: azure-mgmt-authorization (==3.0.0)
Requires-Dist: azure-mgmt-compute (==30.0.0)
Requires-Dist: azure-mgmt-network (>=28.1.0,<29.0.0)
Requires-Dist: azure-mgmt-resource (==23.0.0)
Requires-Dist: black (>=25.1.0,<26.0.0)
Requires-Dist: fastapi (==0.100.0)
Requires-Dist: gunicorn (>=23.0.0,<24.0.0)
Requires-Dist: httpx (>=0.27.0,<0.28.0)
Requires-Dist: mcp[cli] (>=1.7.1,<2.0.0)
Requires-Dist: pydantic (>=2.7.2,<3.0.0)
Requires-Dist: pyyaml (>=6.0.2,<7.0.0)
Requires-Dist: redis (>=5.0.1,<6.0.0)
Requires-Dist: requests (>=2.31.0,<3.0.0)
Requires-Dist: rich (==13.4.2)
Requires-Dist: uvicorn (==0.23.1)
